<?xml version="1.0" encoding="utf-8"?>
<Document>
  <Engineering version="V16" />
  <DocumentInfo>
    <Created>2025-10-24T13:56:31.1933552Z</Created>
    <ExportSetting>WithDefaults</ExportSetting>
    <InstalledProducts>
      <Product>
        <DisplayName>Totally Integrated Automation Portal</DisplayName>
        <DisplayVersion>V16 Update 8</DisplayVersion>
      </Product>
      <OptionPackage>
        <DisplayName>TIA Portal Version Control Interface</DisplayName>
        <DisplayVersion>V16 Update 8</DisplayVersion>
      </OptionPackage>
      <OptionPackage>
        <DisplayName>TIA Portal Openness</DisplayName>
        <DisplayVersion>V16 Update 8</DisplayVersion>
      </OptionPackage>
      <Product>
        <DisplayName>STEP 7 Professional</DisplayName>
        <DisplayVersion>V16 Update 8</DisplayVersion>
      </Product>
      <OptionPackage>
        <DisplayName>STEP 7 Safety</DisplayName>
        <DisplayVersion>V16 Update 7</DisplayVersion>
      </OptionPackage>
      <Product>
        <DisplayName>WinCC Advanced</DisplayName>
        <DisplayVersion>V16 Update 8</DisplayVersion>
      </Product>
    </InstalledProducts>
  </DocumentInfo>
  <SW.Blocks.FB ID="0">
    <AttributeList>
      <AutoNumber>true</AutoNumber>
      <HeaderAuthor />
      <HeaderFamily />
      <HeaderName />
      <HeaderVersion>0.1</HeaderVersion>
      <Interface><Sections xmlns="http://www.siemens.com/automation/Openness/SW/Interface/v4">
  <Section Name="Input" />
  <Section Name="Output">
    <Member Name="Process" Datatype="Struct" Remanence="NonRetain" Accessibility="Public"><AttributeList><BooleanAttribute Name="ExternalAccessible" SystemDefined="true">false</BooleanAttribute><BooleanAttribute Name="ExternalVisible" SystemDefined="true">false</BooleanAttribute><BooleanAttribute Name="ExternalWritable" SystemDefined="true">false</BooleanAttribute></AttributeList><Member Name="Part_In_Position_at_start" Datatype="Bool"><AttributeList><BooleanAttribute Name="ExternalAccessible" SystemDefined="true">false</BooleanAttribute><BooleanAttribute Name="ExternalVisible" SystemDefined="true">false</BooleanAttribute><BooleanAttribute Name="ExternalWritable" SystemDefined="true">false</BooleanAttribute></AttributeList></Member><Member Name="Go_Down_Pick_Up_Part_at_Start" Datatype="Bool"><AttributeList><BooleanAttribute Name="ExternalAccessible" SystemDefined="true">false</BooleanAttribute><BooleanAttribute Name="ExternalVisible" SystemDefined="true">false</BooleanAttribute><BooleanAttribute Name="ExternalWritable" SystemDefined="true">false</BooleanAttribute></AttributeList></Member><Member Name="Part_with_Gripper_at_start" Datatype="Bool"><AttributeList><BooleanAttribute Name="ExternalAccessible" SystemDefined="true">false</BooleanAttribute><BooleanAttribute Name="ExternalVisible" SystemDefined="true">false</BooleanAttribute><BooleanAttribute Name="ExternalWritable" SystemDefined="true">false</BooleanAttribute></AttributeList></Member><Member Name="Do_Pick_Up_at_start" Datatype="Bool"><AttributeList><BooleanAttribute Name="ExternalAccessible" SystemDefined="true">false</BooleanAttribute><BooleanAttribute Name="ExternalVisible" SystemDefined="true">false</BooleanAttribute><BooleanAttribute Name="ExternalWritable" SystemDefined="true">false</BooleanAttribute></AttributeList></Member><Member Name="Gripper_Going_Up_To_be_ready" Datatype="Bool"><AttributeList><BooleanAttribute Name="ExternalAccessible" SystemDefined="true">false</BooleanAttribute><BooleanAttribute Name="ExternalVisible" SystemDefined="true">false</BooleanAttribute><BooleanAttribute Name="ExternalWritable" SystemDefined="true">false</BooleanAttribute></AttributeList></Member><Member Name="Ready_to_Move_to_Stamp" Datatype="Bool"><AttributeList><BooleanAttribute Name="ExternalAccessible" SystemDefined="true">false</BooleanAttribute><BooleanAttribute Name="ExternalVisible" SystemDefined="true">false</BooleanAttribute><BooleanAttribute Name="ExternalWritable" SystemDefined="true">false</BooleanAttribute></AttributeList></Member><Member Name="Ready_to_Move_to_Storage" Datatype="Bool"><AttributeList><BooleanAttribute Name="ExternalAccessible" SystemDefined="true">false</BooleanAttribute><BooleanAttribute Name="ExternalVisible" SystemDefined="true">false</BooleanAttribute><BooleanAttribute Name="ExternalWritable" SystemDefined="true">false</BooleanAttribute></AttributeList></Member><Member Name="Gripper_Going_Down_At_Stamp" Datatype="Bool"><AttributeList><BooleanAttribute Name="ExternalAccessible" SystemDefined="true">false</BooleanAttribute><BooleanAttribute Name="ExternalVisible" SystemDefined="true">false</BooleanAttribute><BooleanAttribute Name="ExternalWritable" SystemDefined="true">false</BooleanAttribute></AttributeList></Member><Member Name="Gripper_Opens_at_Stamp" Datatype="Bool"><AttributeList><BooleanAttribute Name="ExternalAccessible" SystemDefined="true">false</BooleanAttribute><BooleanAttribute Name="ExternalVisible" SystemDefined="true">false</BooleanAttribute><BooleanAttribute Name="ExternalWritable" SystemDefined="true">false</BooleanAttribute></AttributeList></Member><Member Name="Stamp_Done" Datatype="Bool"><AttributeList><BooleanAttribute Name="ExternalAccessible" SystemDefined="true">false</BooleanAttribute><BooleanAttribute Name="ExternalVisible" SystemDefined="true">false</BooleanAttribute><BooleanAttribute Name="ExternalWritable" SystemDefined="true">false</BooleanAttribute></AttributeList></Member><Member Name="Stamping" Datatype="Bool"><AttributeList><BooleanAttribute Name="ExternalAccessible" SystemDefined="true">false</BooleanAttribute><BooleanAttribute Name="ExternalVisible" SystemDefined="true">false</BooleanAttribute><BooleanAttribute Name="ExternalWritable" SystemDefined="true">false</BooleanAttribute></AttributeList></Member><Member Name="Gripper_Closes_at_Stamp" Datatype="Bool"><AttributeList><BooleanAttribute Name="ExternalAccessible" SystemDefined="true">false</BooleanAttribute><BooleanAttribute Name="ExternalVisible" SystemDefined="true">false</BooleanAttribute><BooleanAttribute Name="ExternalWritable" SystemDefined="true">false</BooleanAttribute></AttributeList></Member><Member Name="Gripper_Going_Up_At_Stamp" Datatype="Bool"><AttributeList><BooleanAttribute Name="ExternalAccessible" SystemDefined="true">false</BooleanAttribute><BooleanAttribute Name="ExternalVisible" SystemDefined="true">false</BooleanAttribute><BooleanAttribute Name="ExternalWritable" SystemDefined="true">false</BooleanAttribute></AttributeList></Member><Member Name="Going_To_Storage" Datatype="Bool"><AttributeList><BooleanAttribute Name="ExternalAccessible" SystemDefined="true">false</BooleanAttribute><BooleanAttribute Name="ExternalVisible" SystemDefined="true">false</BooleanAttribute><BooleanAttribute Name="ExternalWritable" SystemDefined="true">false</BooleanAttribute></AttributeList></Member><Member Name="At_Storage" Datatype="Bool"><AttributeList><BooleanAttribute Name="ExternalAccessible" SystemDefined="true">false</BooleanAttribute><BooleanAttribute Name="ExternalVisible" SystemDefined="true">false</BooleanAttribute><BooleanAttribute Name="ExternalWritable" SystemDefined="true">false</BooleanAttribute></AttributeList></Member><Member Name="Release_Part" Datatype="Bool"><AttributeList><BooleanAttribute Name="ExternalAccessible" SystemDefined="true">false</BooleanAttribute><BooleanAttribute Name="ExternalVisible" SystemDefined="true">false</BooleanAttribute><BooleanAttribute Name="ExternalWritable" SystemDefined="true">false</BooleanAttribute></AttributeList></Member></Member>
  </Section>
  <Section Name="InOut" />
  <Section Name="Static" />
  <Section Name="Temp" />
  <Section Name="Constant" />
</Sections></Interface>
      <IsIECCheckEnabled>false</IsIECCheckEnabled>
      <IsRetainMemResEnabled>false</IsRetainMemResEnabled>
      <MemoryLayout>Optimized</MemoryLayout>
      <MemoryReserve>100</MemoryReserve>
      <Name>Steps</Name>
      <Number>3</Number>
      <ProgrammingLanguage>FBD</ProgrammingLanguage>
      <SetENOAutomatically>false</SetENOAutomatically>
      <UDABlockProperties />
      <UDAEnableTagReadback>false</UDAEnableTagReadback>
    </AttributeList>
    <ObjectList>
      <MultilingualText ID="1" CompositionName="Comment">
        <ObjectList>
          <MultilingualTextItem ID="2" CompositionName="Items">
            <AttributeList>
              <Culture>de-DE</Culture>
              <Text />
            </AttributeList>
          </MultilingualTextItem>
        </ObjectList>
      </MultilingualText>
      <SW.Blocks.CompileUnit ID="3" CompositionName="CompileUnits">
        <AttributeList>
          <NetworkSource><FlgNet xmlns="http://www.siemens.com/automation/Openness/SW/NetworkSource/FlgNet/v4">
  <Parts>
    <Access Scope="GlobalVariable" UId="21">
      <Symbol>
        <Component Name="VC" />
        <Component Name="Start Simulation" />
      </Symbol>
    </Access>
    <Access Scope="GlobalVariable" UId="22">
      <Symbol>
        <Component Name="Global DB" />
        <Component Name="Inputs" />
        <Component Name="LightBarrier_Material_AtGripper" />
      </Symbol>
    </Access>
    <Access Scope="GlobalVariable" UId="23">
      <Symbol>
        <Component Name="VC" />
        <Component Name="Start Simulation" />
      </Symbol>
    </Access>
    <Access Scope="GlobalVariable" UId="24">
      <Symbol>
        <Component Name="Global DB" />
        <Component Name="Inputs" />
        <Component Name="LightBarrier_Material_AtGripper" />
      </Symbol>
    </Access>
    <Access Scope="LocalVariable" UId="25">
      <Symbol>
        <Component Name="Process" />
        <Component Name="Gripper_Going_Up_To_be_ready" />
      </Symbol>
    </Access>
    <Access Scope="GlobalVariable" UId="26">
      <Symbol>
        <Component Name="Global DB" />
        <Component Name="Inputs" />
        <Component Name="LightBarrier_Material_AtGripper" />
      </Symbol>
    </Access>
    <Access Scope="GlobalVariable" UId="27">
      <Symbol>
        <Component Name="VC" />
        <Component Name="Start Simulation" />
      </Symbol>
    </Access>
    <Access Scope="TypedConstant" UId="28">
      <Constant>
        <ConstantValue>T#3s</ConstantValue>
      </Constant>
    </Access>
    <Access Scope="LocalVariable" UId="29">
      <Symbol>
        <Component Name="Process" />
        <Component Name="Part_In_Position_at_start" />
      </Symbol>
    </Access>
    <Part Name="A" UId="30">
      <TemplateValue Name="Card" Type="Cardinality">2</TemplateValue>
    </Part>
    <Part Name="A" UId="31">
      <TemplateValue Name="Card" Type="Cardinality">2</TemplateValue>
    </Part>
    <Part Name="TON" Version="1.0" UId="32">
      <Instance Scope="GlobalVariable" UId="33">
        <Component Name="IEC_Timer_0_DB" />
      </Instance>
      <TemplateValue Name="time_type" Type="Type">Time</TemplateValue>
    </Part>
    <Part Name="O" UId="34">
      <TemplateValue Name="Card" Type="Cardinality">4</TemplateValue>
      <Negated Name="in1" />
      <Negated Name="in2" />
    </Part>
    <Part Name="Sr" UId="35" />
  </Parts>
  <Wires>
    <Wire UId="37">
      <IdentCon UId="21" />
      <NameCon UId="30" Name="in1" />
    </Wire>
    <Wire UId="38">
      <IdentCon UId="22" />
      <NameCon UId="30" Name="in2" />
    </Wire>
    <Wire UId="39">
      <NameCon UId="30" Name="out" />
      <NameCon UId="35" Name="s" />
    </Wire>
    <Wire UId="40">
      <IdentCon UId="26" />
      <NameCon UId="31" Name="in1" />
    </Wire>
    <Wire UId="41">
      <IdentCon UId="27" />
      <NameCon UId="31" Name="in2" />
    </Wire>
    <Wire UId="42">
      <NameCon UId="31" Name="out" />
      <NameCon UId="32" Name="IN" />
    </Wire>
    <Wire UId="43">
      <IdentCon UId="28" />
      <NameCon UId="32" Name="PT" />
    </Wire>
    <Wire UId="44">
      <NameCon UId="32" Name="ET" />
      <OpenCon UId="36" />
    </Wire>
    <Wire UId="45">
      <NameCon UId="32" Name="Q" />
      <NameCon UId="34" Name="in4" />
    </Wire>
    <Wire UId="46">
      <IdentCon UId="23" />
      <NameCon UId="34" Name="in1" />
    </Wire>
    <Wire UId="47">
      <IdentCon UId="24" />
      <NameCon UId="34" Name="in2" />
    </Wire>
    <Wire UId="48">
      <IdentCon UId="25" />
      <NameCon UId="34" Name="in3" />
    </Wire>
    <Wire UId="49">
      <NameCon UId="34" Name="out" />
      <NameCon UId="35" Name="r1" />
    </Wire>
    <Wire UId="50">
      <IdentCon UId="29" />
      <NameCon UId="35" Name="operand" />
    </Wire>
  </Wires>
</FlgNet></NetworkSource>
          <ProgrammingLanguage>FBD</ProgrammingLanguage>
        </AttributeList>
        <ObjectList>
          <MultilingualText ID="4" CompositionName="Comment">
            <ObjectList>
              <MultilingualTextItem ID="5" CompositionName="Items">
                <AttributeList>
                  <Culture>de-DE</Culture>
                  <Text />
                </AttributeList>
              </MultilingualTextItem>
            </ObjectList>
          </MultilingualText>
          <MultilingualText ID="6" CompositionName="Title">
            <ObjectList>
              <MultilingualTextItem ID="7" CompositionName="Items">
                <AttributeList>
                  <Culture>de-DE</Culture>
                  <Text />
                </AttributeList>
              </MultilingualTextItem>
            </ObjectList>
          </MultilingualText>
        </ObjectList>
      </SW.Blocks.CompileUnit>
      <SW.Blocks.CompileUnit ID="8" CompositionName="CompileUnits">
        <AttributeList>
          <NetworkSource><FlgNet xmlns="http://www.siemens.com/automation/Openness/SW/NetworkSource/FlgNet/v4">
  <Parts>
    <Access Scope="GlobalVariable" UId="21">
      <Symbol>
        <Component Name="VC" />
        <Component Name="Start Simulation" />
      </Symbol>
    </Access>
    <Access Scope="GlobalVariable" UId="22">
      <Symbol>
        <Component Name="Global DB" />
        <Component Name="Inputs" />
        <Component Name="I_Cylinder_Gripper_Up" />
      </Symbol>
    </Access>
    <Access Scope="LocalVariable" UId="23">
      <Symbol>
        <Component Name="Process" />
        <Component Name="Part_In_Position_at_start" />
      </Symbol>
    </Access>
    <Access Scope="TypedConstant" UId="24">
      <Constant>
        <ConstantValue>T#1s</ConstantValue>
      </Constant>
    </Access>
    <Access Scope="GlobalVariable" UId="25">
      <Symbol>
        <Component Name="VC" />
        <Component Name="Start Simulation" />
      </Symbol>
    </Access>
    <Access Scope="GlobalVariable" UId="26">
      <Symbol>
        <Component Name="Global DB" />
        <Component Name="Inputs" />
        <Component Name="I_Cylinder_Gripper_Down" />
      </Symbol>
    </Access>
    <Access Scope="GlobalVariable" UId="27">
      <Symbol>
        <Component Name="Global DB" />
        <Component Name="Inputs" />
        <Component Name="I_Axis_Homing_Left" />
      </Symbol>
    </Access>
    <Access Scope="LocalVariable" UId="28">
      <Symbol>
        <Component Name="Process" />
        <Component Name="Go_Down_Pick_Up_Part_at_Start" />
      </Symbol>
    </Access>
    <Part Name="A" UId="29">
      <TemplateValue Name="Card" Type="Cardinality">3</TemplateValue>
    </Part>
    <Part Name="TON" Version="1.0" UId="30">
      <Instance Scope="GlobalVariable" UId="31">
        <Component Name="IEC_Timer_0_DB_13" />
      </Instance>
      <TemplateValue Name="time_type" Type="Type">Time</TemplateValue>
    </Part>
    <Part Name="O" UId="32">
      <TemplateValue Name="Card" Type="Cardinality">3</TemplateValue>
      <Negated Name="in1" />
      <Negated Name="in3" />
    </Part>
    <Part Name="Sr" UId="33" />
  </Parts>
  <Wires>
    <Wire UId="35">
      <IdentCon UId="21" />
      <NameCon UId="29" Name="in1" />
    </Wire>
    <Wire UId="36">
      <IdentCon UId="22" />
      <NameCon UId="29" Name="in2" />
    </Wire>
    <Wire UId="37">
      <IdentCon UId="23" />
      <NameCon UId="29" Name="in3" />
    </Wire>
    <Wire UId="38">
      <NameCon UId="29" Name="out" />
      <NameCon UId="30" Name="IN" />
    </Wire>
    <Wire UId="39">
      <IdentCon UId="24" />
      <NameCon UId="30" Name="PT" />
    </Wire>
    <Wire UId="40">
      <NameCon UId="30" Name="ET" />
      <OpenCon UId="34" />
    </Wire>
    <Wire UId="41">
      <NameCon UId="30" Name="Q" />
      <NameCon UId="33" Name="s" />
    </Wire>
    <Wire UId="42">
      <IdentCon UId="25" />
      <NameCon UId="32" Name="in1" />
    </Wire>
    <Wire UId="43">
      <IdentCon UId="26" />
      <NameCon UId="32" Name="in2" />
    </Wire>
    <Wire UId="44">
      <IdentCon UId="27" />
      <NameCon UId="32" Name="in3" />
    </Wire>
    <Wire UId="45">
      <NameCon UId="32" Name="out" />
      <NameCon UId="33" Name="r1" />
    </Wire>
    <Wire UId="46">
      <IdentCon UId="28" />
      <NameCon UId="33" Name="operand" />
    </Wire>
  </Wires>
</FlgNet></NetworkSource>
          <ProgrammingLanguage>FBD</ProgrammingLanguage>
        </AttributeList>
        <ObjectList>
          <MultilingualText ID="9" CompositionName="Comment">
            <ObjectList>
              <MultilingualTextItem ID="A" CompositionName="Items">
                <AttributeList>
                  <Culture>de-DE</Culture>
                  <Text />
                </AttributeList>
              </MultilingualTextItem>
            </ObjectList>
          </MultilingualText>
          <MultilingualText ID="B" CompositionName="Title">
            <ObjectList>
              <MultilingualTextItem ID="C" CompositionName="Items">
                <AttributeList>
                  <Culture>de-DE</Culture>
                  <Text />
                </AttributeList>
              </MultilingualTextItem>
            </ObjectList>
          </MultilingualText>
        </ObjectList>
      </SW.Blocks.CompileUnit>
      <SW.Blocks.CompileUnit ID="D" CompositionName="CompileUnits">
        <AttributeList>
          <NetworkSource><FlgNet xmlns="http://www.siemens.com/automation/Openness/SW/NetworkSource/FlgNet/v4">
  <Parts>
    <Access Scope="GlobalVariable" UId="21">
      <Symbol>
        <Component Name="VC" />
        <Component Name="Start Simulation" />
      </Symbol>
    </Access>
    <Access Scope="GlobalVariable" UId="22">
      <Symbol>
        <Component Name="Global DB" />
        <Component Name="Inputs" />
        <Component Name="I_Cylinder_Gripper_Down" />
      </Symbol>
    </Access>
    <Access Scope="TypedConstant" UId="23">
      <Constant>
        <ConstantValue>T#1s</ConstantValue>
      </Constant>
    </Access>
    <Access Scope="GlobalVariable" UId="24">
      <Symbol>
        <Component Name="VC" />
        <Component Name="Start Simulation" />
      </Symbol>
    </Access>
    <Access Scope="LocalVariable" UId="25">
      <Symbol>
        <Component Name="Process" />
        <Component Name="Gripper_Going_Up_To_be_ready" />
      </Symbol>
    </Access>
    <Access Scope="LocalVariable" UId="26">
      <Symbol>
        <Component Name="Process" />
        <Component Name="Do_Pick_Up_at_start" />
      </Symbol>
    </Access>
    <Part Name="A" UId="27">
      <TemplateValue Name="Card" Type="Cardinality">2</TemplateValue>
    </Part>
    <Part Name="TON" Version="1.0" UId="28">
      <Instance Scope="GlobalVariable" UId="29">
        <Component Name="IEC_Timer_0_DB_14" />
      </Instance>
      <TemplateValue Name="time_type" Type="Type">Time</TemplateValue>
    </Part>
    <Part Name="O" UId="30">
      <TemplateValue Name="Card" Type="Cardinality">2</TemplateValue>
      <Negated Name="in1" />
    </Part>
    <Part Name="Sr" UId="31" />
  </Parts>
  <Wires>
    <Wire UId="33">
      <IdentCon UId="21" />
      <NameCon UId="27" Name="in1" />
    </Wire>
    <Wire UId="34">
      <IdentCon UId="22" />
      <NameCon UId="27" Name="in2" />
    </Wire>
    <Wire UId="35">
      <NameCon UId="27" Name="out" />
      <NameCon UId="28" Name="IN" />
    </Wire>
    <Wire UId="36">
      <IdentCon UId="23" />
      <NameCon UId="28" Name="PT" />
    </Wire>
    <Wire UId="37">
      <NameCon UId="28" Name="ET" />
      <OpenCon UId="32" />
    </Wire>
    <Wire UId="38">
      <NameCon UId="28" Name="Q" />
      <NameCon UId="31" Name="s" />
    </Wire>
    <Wire UId="39">
      <IdentCon UId="24" />
      <NameCon UId="30" Name="in1" />
    </Wire>
    <Wire UId="40">
      <IdentCon UId="25" />
      <NameCon UId="30" Name="in2" />
    </Wire>
    <Wire UId="41">
      <NameCon UId="30" Name="out" />
      <NameCon UId="31" Name="r1" />
    </Wire>
    <Wire UId="42">
      <IdentCon UId="26" />
      <NameCon UId="31" Name="operand" />
    </Wire>
  </Wires>
</FlgNet></NetworkSource>
          <ProgrammingLanguage>FBD</ProgrammingLanguage>
        </AttributeList>
        <ObjectList>
          <MultilingualText ID="E" CompositionName="Comment">
            <ObjectList>
              <MultilingualTextItem ID="F" CompositionName="Items">
                <AttributeList>
                  <Culture>de-DE</Culture>
                  <Text />
                </AttributeList>
              </MultilingualTextItem>
            </ObjectList>
          </MultilingualText>
          <MultilingualText ID="10" CompositionName="Title">
            <ObjectList>
              <MultilingualTextItem ID="11" CompositionName="Items">
                <AttributeList>
                  <Culture>de-DE</Culture>
                  <Text />
                </AttributeList>
              </MultilingualTextItem>
            </ObjectList>
          </MultilingualText>
        </ObjectList>
      </SW.Blocks.CompileUnit>
      <SW.Blocks.CompileUnit ID="12" CompositionName="CompileUnits">
        <AttributeList>
          <NetworkSource><FlgNet xmlns="http://www.siemens.com/automation/Openness/SW/NetworkSource/FlgNet/v4">
  <Parts>
    <Access Scope="LocalVariable" UId="21">
      <Symbol>
        <Component Name="Process" />
        <Component Name="Do_Pick_Up_at_start" />
      </Symbol>
    </Access>
    <Access Scope="GlobalVariable" UId="22">
      <Symbol>
        <Component Name="VC" />
        <Component Name="Start Simulation" />
      </Symbol>
    </Access>
    <Access Scope="TypedConstant" UId="23">
      <Constant>
        <ConstantValue>T#1s</ConstantValue>
      </Constant>
    </Access>
    <Access Scope="GlobalVariable" UId="24">
      <Symbol>
        <Component Name="VC" />
        <Component Name="Start Simulation" />
      </Symbol>
    </Access>
    <Access Scope="LocalVariable" UId="25">
      <Symbol>
        <Component Name="Process" />
        <Component Name="Ready_to_Move_to_Stamp" />
      </Symbol>
    </Access>
    <Access Scope="LocalVariable" UId="26">
      <Symbol>
        <Component Name="Process" />
        <Component Name="Ready_to_Move_to_Storage" />
      </Symbol>
    </Access>
    <Access Scope="GlobalVariable" UId="27">
      <Symbol>
        <Component Name="Global DB" />
        <Component Name="Inputs" />
        <Component Name="I_Gripper_at_Stamp" />
      </Symbol>
    </Access>
    <Access Scope="GlobalVariable" UId="28">
      <Symbol>
        <Component Name="Global DB" />
        <Component Name="Inputs" />
        <Component Name="LightBarrier_Material_AtGripper" />
      </Symbol>
    </Access>
    <Access Scope="GlobalVariable" UId="29">
      <Symbol>
        <Component Name="VC" />
        <Component Name="Start Simulation" />
      </Symbol>
    </Access>
    <Access Scope="TypedConstant" UId="30">
      <Constant>
        <ConstantValue>T#10s</ConstantValue>
      </Constant>
    </Access>
    <Access Scope="LocalVariable" UId="31">
      <Symbol>
        <Component Name="Process" />
        <Component Name="Gripper_Going_Up_To_be_ready" />
      </Symbol>
    </Access>
    <Part Name="A" UId="32">
      <TemplateValue Name="Card" Type="Cardinality">2</TemplateValue>
    </Part>
    <Part Name="TON" Version="1.0" UId="33">
      <Instance Scope="GlobalVariable" UId="34">
        <Component Name="IEC_Timer_0_DB_15" />
      </Instance>
      <TemplateValue Name="time_type" Type="Type">Time</TemplateValue>
    </Part>
    <Part Name="A" UId="35">
      <TemplateValue Name="Card" Type="Cardinality">2</TemplateValue>
    </Part>
    <Part Name="TON" Version="1.0" UId="36">
      <Instance Scope="GlobalVariable" UId="37">
        <Component Name="IEC_Timer_0_DB_4" />
      </Instance>
      <TemplateValue Name="time_type" Type="Type">Time</TemplateValue>
    </Part>
    <Part Name="O" UId="38">
      <TemplateValue Name="Card" Type="Cardinality">5</TemplateValue>
      <Negated Name="in1" />
    </Part>
    <Part Name="Sr" UId="39" />
  </Parts>
  <Wires>
    <Wire UId="42">
      <IdentCon UId="21" />
      <NameCon UId="32" Name="in1" />
    </Wire>
    <Wire UId="43">
      <IdentCon UId="22" />
      <NameCon UId="32" Name="in2" />
    </Wire>
    <Wire UId="44">
      <NameCon UId="32" Name="out" />
      <NameCon UId="33" Name="IN" />
    </Wire>
    <Wire UId="45">
      <IdentCon UId="23" />
      <NameCon UId="33" Name="PT" />
    </Wire>
    <Wire UId="46">
      <NameCon UId="33" Name="ET" />
      <OpenCon UId="40" />
    </Wire>
    <Wire UId="47">
      <NameCon UId="33" Name="Q" />
      <NameCon UId="39" Name="s" />
    </Wire>
    <Wire UId="48">
      <IdentCon UId="28" />
      <NameCon UId="35" Name="in1" />
    </Wire>
    <Wire UId="49">
      <IdentCon UId="29" />
      <NameCon UId="35" Name="in2" />
    </Wire>
    <Wire UId="50">
      <NameCon UId="35" Name="out" />
      <NameCon UId="36" Name="IN" />
    </Wire>
    <Wire UId="51">
      <IdentCon UId="30" />
      <NameCon UId="36" Name="PT" />
    </Wire>
    <Wire UId="52">
      <NameCon UId="36" Name="ET" />
      <OpenCon UId="41" />
    </Wire>
    <Wire UId="53">
      <NameCon UId="36" Name="Q" />
      <NameCon UId="38" Name="in5" />
    </Wire>
    <Wire UId="54">
      <IdentCon UId="24" />
      <NameCon UId="38" Name="in1" />
    </Wire>
    <Wire UId="55">
      <IdentCon UId="25" />
      <NameCon UId="38" Name="in2" />
    </Wire>
    <Wire UId="56">
      <IdentCon UId="26" />
      <NameCon UId="38" Name="in3" />
    </Wire>
    <Wire UId="57">
      <IdentCon UId="27" />
      <NameCon UId="38" Name="in4" />
    </Wire>
    <Wire UId="58">
      <NameCon UId="38" Name="out" />
      <NameCon UId="39" Name="r1" />
    </Wire>
    <Wire UId="59">
      <IdentCon UId="31" />
      <NameCon UId="39" Name="operand" />
    </Wire>
  </Wires>
</FlgNet></NetworkSource>
          <ProgrammingLanguage>FBD</ProgrammingLanguage>
        </AttributeList>
        <ObjectList>
          <MultilingualText ID="13" CompositionName="Comment">
            <ObjectList>
              <MultilingualTextItem ID="14" CompositionName="Items">
                <AttributeList>
                  <Culture>de-DE</Culture>
                  <Text />
                </AttributeList>
              </MultilingualTextItem>
            </ObjectList>
          </MultilingualText>
          <MultilingualText ID="15" CompositionName="Title">
            <ObjectList>
              <MultilingualTextItem ID="16" CompositionName="Items">
                <AttributeList>
                  <Culture>de-DE</Culture>
                  <Text />
                </AttributeList>
              </MultilingualTextItem>
            </ObjectList>
          </MultilingualText>
        </ObjectList>
      </SW.Blocks.CompileUnit>
      <SW.Blocks.CompileUnit ID="17" CompositionName="CompileUnits">
        <AttributeList>
          <NetworkSource><FlgNet xmlns="http://www.siemens.com/automation/Openness/SW/NetworkSource/FlgNet/v4">
  <Parts>
    <Access Scope="GlobalVariable" UId="21">
      <Symbol>
        <Component Name="VC" />
        <Component Name="Start Simulation" />
      </Symbol>
    </Access>
    <Access Scope="GlobalVariable" UId="22">
      <Symbol>
        <Component Name="Global DB" />
        <Component Name="Inputs" />
        <Component Name="I_Conveyor_Metal" />
      </Symbol>
    </Access>
    <Access Scope="GlobalVariable" UId="23">
      <Symbol>
        <Component Name="Global DB" />
        <Component Name="Inputs" />
        <Component Name="I_Stamp_Up" />
      </Symbol>
    </Access>
    <Access Scope="GlobalVariable" UId="24">
      <Symbol>
        <Component Name="Global DB" />
        <Component Name="Inputs" />
        <Component Name="I_Cylinder_Gripper_Up" />
      </Symbol>
    </Access>
    <Access Scope="TypedConstant" UId="25">
      <Constant>
        <ConstantValue>T#1s</ConstantValue>
      </Constant>
    </Access>
    <Access Scope="GlobalVariable" UId="26">
      <Symbol>
        <Component Name="VC" />
        <Component Name="Start Simulation" />
      </Symbol>
    </Access>
    <Access Scope="GlobalVariable" UId="27">
      <Symbol>
        <Component Name="Global DB" />
        <Component Name="Inputs" />
        <Component Name="I_Stamp_Up" />
      </Symbol>
    </Access>
    <Access Scope="GlobalVariable" UId="28">
      <Symbol>
        <Component Name="Global DB" />
        <Component Name="Inputs" />
        <Component Name="I_Cylinder_Gripper_Down" />
      </Symbol>
    </Access>
    <Access Scope="GlobalVariable" UId="29">
      <Symbol>
        <Component Name="Global DB" />
        <Component Name="Inputs" />
        <Component Name="I_Conveyor_Metal" />
      </Symbol>
    </Access>
    <Access Scope="GlobalVariable" UId="30">
      <Symbol>
        <Component Name="Global DB" />
        <Component Name="Inputs" />
        <Component Name="I_Conveyor_Plastic" />
      </Symbol>
    </Access>
    <Access Scope="LocalVariable" UId="31">
      <Symbol>
        <Component Name="Process" />
        <Component Name="Ready_to_Move_to_Storage" />
      </Symbol>
    </Access>
    <Access Scope="LocalVariable" UId="32">
      <Symbol>
        <Component Name="Process" />
        <Component Name="Gripper_Going_Down_At_Stamp" />
      </Symbol>
    </Access>
    <Access Scope="LocalVariable" UId="33">
      <Symbol>
        <Component Name="Process" />
        <Component Name="Ready_to_Move_to_Stamp" />
      </Symbol>
    </Access>
    <Access Scope="GlobalVariable" UId="34">
      <Symbol>
        <Component Name="VC" />
        <Component Name="Start Simulation" />
      </Symbol>
    </Access>
    <Access Scope="GlobalVariable" UId="35">
      <Symbol>
        <Component Name="Global DB" />
        <Component Name="Inputs" />
        <Component Name="I_Conveyor_Plastic" />
      </Symbol>
    </Access>
    <Access Scope="GlobalVariable" UId="36">
      <Symbol>
        <Component Name="Global DB" />
        <Component Name="Inputs" />
        <Component Name="I_Stamp_Up" />
      </Symbol>
    </Access>
    <Access Scope="GlobalVariable" UId="37">
      <Symbol>
        <Component Name="Global DB" />
        <Component Name="Inputs" />
        <Component Name="I_Cylinder_Gripper_Up" />
      </Symbol>
    </Access>
    <Access Scope="LocalVariable" UId="38">
      <Symbol>
        <Component Name="Process" />
        <Component Name="Stamp_Done" />
      </Symbol>
    </Access>
    <Access Scope="GlobalVariable" UId="39">
      <Symbol>
        <Component Name="Global DB" />
        <Component Name="Inputs" />
        <Component Name="I_Cylinder_Gripper_Up" />
      </Symbol>
    </Access>
    <Access Scope="GlobalVariable" UId="40">
      <Symbol>
        <Component Name="Global DB" />
        <Component Name="Inputs" />
        <Component Name="I_Conveyor_Metal" />
      </Symbol>
    </Access>
    <Access Scope="TypedConstant" UId="41">
      <Constant>
        <ConstantValue>T#1s</ConstantValue>
      </Constant>
    </Access>
    <Access Scope="GlobalVariable" UId="42">
      <Symbol>
        <Component Name="VC" />
        <Component Name="Start Simulation" />
      </Symbol>
    </Access>
    <Access Scope="GlobalVariable" UId="43">
      <Symbol>
        <Component Name="Global DB" />
        <Component Name="Inputs" />
        <Component Name="I_Stamp_Up" />
      </Symbol>
    </Access>
    <Access Scope="GlobalVariable" UId="44">
      <Symbol>
        <Component Name="Global DB" />
        <Component Name="Inputs" />
        <Component Name="I_Cylinder_Gripper_Down" />
      </Symbol>
    </Access>
    <Access Scope="LocalVariable" UId="45">
      <Symbol>
        <Component Name="Process" />
        <Component Name="Ready_to_Move_to_Storage" />
      </Symbol>
    </Access>
    <Part Name="A" UId="46">
      <TemplateValue Name="Card" Type="Cardinality">4</TemplateValue>
    </Part>
    <Part Name="TON" Version="1.0" UId="47">
      <Instance Scope="GlobalVariable" UId="48">
        <Component Name="IEC_Timer_0_DB_16" />
      </Instance>
      <TemplateValue Name="time_type" Type="Type">Time</TemplateValue>
    </Part>
    <Part Name="O" UId="49">
      <TemplateValue Name="Card" Type="Cardinality">7</TemplateValue>
      <Negated Name="in1" />
      <Negated Name="in2" />
      <Negated Name="in4" />
    </Part>
    <Part Name="Sr" UId="50" />
    <Part Name="A" UId="51">
      <TemplateValue Name="Card" Type="Cardinality">4</TemplateValue>
    </Part>
    <Part Name="A" UId="52">
      <TemplateValue Name="Card" Type="Cardinality">3</TemplateValue>
    </Part>
    <Part Name="O" UId="53">
      <TemplateValue Name="Card" Type="Cardinality">2</TemplateValue>
    </Part>
    <Part Name="TON" Version="1.0" UId="54">
      <Instance Scope="GlobalVariable" UId="55">
        <Component Name="IEC_Timer_0_DB_17" />
      </Instance>
      <TemplateValue Name="time_type" Type="Type">Time</TemplateValue>
    </Part>
    <Part Name="O" UId="56">
      <TemplateValue Name="Card" Type="Cardinality">3</TemplateValue>
      <Negated Name="in1" />
      <Negated Name="in2" />
    </Part>
    <Part Name="Sr" UId="57" />
  </Parts>
  <Wires>
    <Wire UId="60">
      <IdentCon UId="21" />
      <NameCon UId="46" Name="in1" />
    </Wire>
    <Wire UId="61">
      <IdentCon UId="22" />
      <NameCon UId="46" Name="in2" />
    </Wire>
    <Wire UId="62">
      <IdentCon UId="23" />
      <NameCon UId="46" Name="in3" />
    </Wire>
    <Wire UId="63">
      <IdentCon UId="24" />
      <NameCon UId="46" Name="in4" />
    </Wire>
    <Wire UId="64">
      <NameCon UId="46" Name="out" />
      <NameCon UId="47" Name="IN" />
    </Wire>
    <Wire UId="65">
      <IdentCon UId="25" />
      <NameCon UId="47" Name="PT" />
    </Wire>
    <Wire UId="66">
      <NameCon UId="47" Name="ET" />
      <OpenCon UId="58" />
    </Wire>
    <Wire UId="67">
      <NameCon UId="47" Name="Q" />
      <NameCon UId="50" Name="s" />
    </Wire>
    <Wire UId="68">
      <IdentCon UId="26" />
      <NameCon UId="49" Name="in1" />
    </Wire>
    <Wire UId="69">
      <IdentCon UId="27" />
      <NameCon UId="49" Name="in2" />
    </Wire>
    <Wire UId="70">
      <IdentCon UId="28" />
      <NameCon UId="49" Name="in3" />
    </Wire>
    <Wire UId="71">
      <IdentCon UId="29" />
      <NameCon UId="49" Name="in4" />
    </Wire>
    <Wire UId="72">
      <IdentCon UId="30" />
      <NameCon UId="49" Name="in5" />
    </Wire>
    <Wire UId="73">
      <IdentCon UId="31" />
      <NameCon UId="49" Name="in6" />
    </Wire>
    <Wire UId="74">
      <IdentCon UId="32" />
      <NameCon UId="49" Name="in7" />
    </Wire>
    <Wire UId="75">
      <NameCon UId="49" Name="out" />
      <NameCon UId="50" Name="r1" />
    </Wire>
    <Wire UId="76">
      <IdentCon UId="33" />
      <NameCon UId="50" Name="operand" />
    </Wire>
    <Wire UId="77">
      <IdentCon UId="34" />
      <NameCon UId="51" Name="in1" />
    </Wire>
    <Wire UId="78">
      <IdentCon UId="35" />
      <NameCon UId="51" Name="in2" />
    </Wire>
    <Wire UId="79">
      <IdentCon UId="36" />
      <NameCon UId="51" Name="in3" />
    </Wire>
    <Wire UId="80">
      <IdentCon UId="37" />
      <NameCon UId="51" Name="in4" />
    </Wire>
    <Wire UId="81">
      <NameCon UId="51" Name="out" />
      <NameCon UId="53" Name="in1" />
    </Wire>
    <Wire UId="82">
      <IdentCon UId="38" />
      <NameCon UId="52" Name="in1" />
    </Wire>
    <Wire UId="83">
      <IdentCon UId="39" />
      <NameCon UId="52" Name="in2" />
    </Wire>
    <Wire UId="84">
      <IdentCon UId="40" />
      <NameCon UId="52" Name="in3" />
    </Wire>
    <Wire UId="85">
      <NameCon UId="52" Name="out" />
      <NameCon UId="53" Name="in2" />
    </Wire>
    <Wire UId="86">
      <NameCon UId="53" Name="out" />
      <NameCon UId="54" Name="IN" />
    </Wire>
    <Wire UId="87">
      <IdentCon UId="41" />
      <NameCon UId="54" Name="PT" />
    </Wire>
    <Wire UId="88">
      <NameCon UId="54" Name="ET" />
      <OpenCon UId="59" />
    </Wire>
    <Wire UId="89">
      <NameCon UId="54" Name="Q" />
      <NameCon UId="57" Name="s" />
    </Wire>
    <Wire UId="90">
      <IdentCon UId="42" />
      <NameCon UId="56" Name="in1" />
    </Wire>
    <Wire UId="91">
      <IdentCon UId="43" />
      <NameCon UId="56" Name="in2" />
    </Wire>
    <Wire UId="92">
      <IdentCon UId="44" />
      <NameCon UId="56" Name="in3" />
    </Wire>
    <Wire UId="93">
      <NameCon UId="56" Name="out" />
      <NameCon UId="57" Name="r1" />
    </Wire>
    <Wire UId="94">
      <IdentCon UId="45" />
      <NameCon UId="57" Name="operand" />
    </Wire>
  </Wires>
</FlgNet></NetworkSource>
          <ProgrammingLanguage>FBD</ProgrammingLanguage>
        </AttributeList>
        <ObjectList>
          <MultilingualText ID="18" CompositionName="Comment">
            <ObjectList>
              <MultilingualTextItem ID="19" CompositionName="Items">
                <AttributeList>
                  <Culture>de-DE</Culture>
                  <Text />
                </AttributeList>
              </MultilingualTextItem>
            </ObjectList>
          </MultilingualText>
          <MultilingualText ID="1A" CompositionName="Title">
            <ObjectList>
              <MultilingualTextItem ID="1B" CompositionName="Items">
                <AttributeList>
                  <Culture>de-DE</Culture>
                  <Text />
                </AttributeList>
              </MultilingualTextItem>
            </ObjectList>
          </MultilingualText>
        </ObjectList>
      </SW.Blocks.CompileUnit>
      <SW.Blocks.CompileUnit ID="1C" CompositionName="CompileUnits">
        <AttributeList>
          <NetworkSource><FlgNet xmlns="http://www.siemens.com/automation/Openness/SW/NetworkSource/FlgNet/v4">
  <Parts>
    <Access Scope="GlobalVariable" UId="21">
      <Symbol>
        <Component Name="VC" />
        <Component Name="Start Simulation" />
      </Symbol>
    </Access>
    <Access Scope="GlobalVariable" UId="22">
      <Symbol>
        <Component Name="Global DB" />
        <Component Name="Inputs" />
        <Component Name="I_Gripper_at_Stamp" />
      </Symbol>
    </Access>
    <Access Scope="GlobalVariable" UId="23">
      <Symbol>
        <Component Name="Global DB" />
        <Component Name="Inputs" />
        <Component Name="I_Stamp_Up" />
      </Symbol>
    </Access>
    <Access Scope="GlobalVariable" UId="24">
      <Symbol>
        <Component Name="Global DB" />
        <Component Name="Inputs" />
        <Component Name="I_Conveyor_Metal" />
      </Symbol>
    </Access>
    <Access Scope="GlobalVariable" UId="25">
      <Symbol>
        <Component Name="Global DB" />
        <Component Name="Inputs" />
        <Component Name="I_Cylinder_Gripper_Up" />
      </Symbol>
    </Access>
    <Access Scope="TypedConstant" UId="26">
      <Constant>
        <ConstantValue>T#1s</ConstantValue>
      </Constant>
    </Access>
    <Access Scope="GlobalVariable" UId="27">
      <Symbol>
        <Component Name="VC" />
        <Component Name="Start Simulation" />
      </Symbol>
    </Access>
    <Access Scope="LocalVariable" UId="28">
      <Symbol>
        <Component Name="Process" />
        <Component Name="Stamp_Done" />
      </Symbol>
    </Access>
    <Access Scope="LocalVariable" UId="29">
      <Symbol>
        <Component Name="Process" />
        <Component Name="Stamping" />
      </Symbol>
    </Access>
    <Access Scope="LocalVariable" UId="30">
      <Symbol>
        <Component Name="Process" />
        <Component Name="Gripper_Opens_at_Stamp" />
      </Symbol>
    </Access>
    <Access Scope="GlobalVariable" UId="31">
      <Symbol>
        <Component Name="Global DB" />
        <Component Name="Inputs" />
        <Component Name="I_Cylinder_Gripper_Down" />
      </Symbol>
    </Access>
    <Access Scope="LocalVariable" UId="32">
      <Symbol>
        <Component Name="Process" />
        <Component Name="Gripper_Opens_at_Stamp" />
      </Symbol>
    </Access>
    <Access Scope="LocalVariable" UId="33">
      <Symbol>
        <Component Name="Process" />
        <Component Name="Gripper_Going_Down_At_Stamp" />
      </Symbol>
    </Access>
    <Part Name="A" UId="34">
      <TemplateValue Name="Card" Type="Cardinality">5</TemplateValue>
    </Part>
    <Part Name="TON" Version="1.0" UId="35">
      <Instance Scope="GlobalVariable" UId="36">
        <Component Name="IEC_Timer_0_DB_18" />
      </Instance>
      <TemplateValue Name="time_type" Type="Type">Time</TemplateValue>
    </Part>
    <Part Name="O" UId="37">
      <TemplateValue Name="Card" Type="Cardinality">6</TemplateValue>
      <Negated Name="in1" />
    </Part>
    <Part Name="Sr" UId="38" />
  </Parts>
  <Wires>
    <Wire UId="40">
      <IdentCon UId="21" />
      <NameCon UId="34" Name="in1" />
    </Wire>
    <Wire UId="41">
      <IdentCon UId="22" />
      <NameCon UId="34" Name="in2" />
    </Wire>
    <Wire UId="42">
      <IdentCon UId="23" />
      <NameCon UId="34" Name="in3" />
    </Wire>
    <Wire UId="43">
      <IdentCon UId="24" />
      <NameCon UId="34" Name="in4" />
    </Wire>
    <Wire UId="44">
      <IdentCon UId="25" />
      <NameCon UId="34" Name="in5" />
    </Wire>
    <Wire UId="45">
      <NameCon UId="34" Name="out" />
      <NameCon UId="35" Name="IN" />
    </Wire>
    <Wire UId="46">
      <IdentCon UId="26" />
      <NameCon UId="35" Name="PT" />
    </Wire>
    <Wire UId="47">
      <NameCon UId="35" Name="ET" />
      <OpenCon UId="39" />
    </Wire>
    <Wire UId="48">
      <NameCon UId="35" Name="Q" />
      <NameCon UId="38" Name="s" />
    </Wire>
    <Wire UId="49">
      <IdentCon UId="27" />
      <NameCon UId="37" Name="in1" />
    </Wire>
    <Wire UId="50">
      <IdentCon UId="28" />
      <NameCon UId="37" Name="in2" />
    </Wire>
    <Wire UId="51">
      <IdentCon UId="29" />
      <NameCon UId="37" Name="in3" />
    </Wire>
    <Wire UId="52">
      <IdentCon UId="30" />
      <NameCon UId="37" Name="in4" />
    </Wire>
    <Wire UId="53">
      <IdentCon UId="31" />
      <NameCon UId="37" Name="in5" />
    </Wire>
    <Wire UId="54">
      <IdentCon UId="32" />
      <NameCon UId="37" Name="in6" />
    </Wire>
    <Wire UId="55">
      <NameCon UId="37" Name="out" />
      <NameCon UId="38" Name="r1" />
    </Wire>
    <Wire UId="56">
      <IdentCon UId="33" />
      <NameCon UId="38" Name="operand" />
    </Wire>
  </Wires>
</FlgNet></NetworkSource>
          <ProgrammingLanguage>FBD</ProgrammingLanguage>
        </AttributeList>
        <ObjectList>
          <MultilingualText ID="1D" CompositionName="Comment">
            <ObjectList>
              <MultilingualTextItem ID="1E" CompositionName="Items">
                <AttributeList>
                  <Culture>de-DE</Culture>
                  <Text />
                </AttributeList>
              </MultilingualTextItem>
            </ObjectList>
          </MultilingualText>
          <MultilingualText ID="1F" CompositionName="Title">
            <ObjectList>
              <MultilingualTextItem ID="20" CompositionName="Items">
                <AttributeList>
                  <Culture>de-DE</Culture>
                  <Text />
                </AttributeList>
              </MultilingualTextItem>
            </ObjectList>
          </MultilingualText>
        </ObjectList>
      </SW.Blocks.CompileUnit>
      <SW.Blocks.CompileUnit ID="21" CompositionName="CompileUnits">
        <AttributeList>
          <NetworkSource><FlgNet xmlns="http://www.siemens.com/automation/Openness/SW/NetworkSource/FlgNet/v4">
  <Parts>
    <Access Scope="GlobalVariable" UId="21">
      <Symbol>
        <Component Name="VC" />
        <Component Name="Start Simulation" />
      </Symbol>
    </Access>
    <Access Scope="GlobalVariable" UId="22">
      <Symbol>
        <Component Name="Global DB" />
        <Component Name="Inputs" />
        <Component Name="I_Cylinder_Gripper_Down" />
      </Symbol>
    </Access>
    <Access Scope="GlobalVariable" UId="23">
      <Symbol>
        <Component Name="Global DB" />
        <Component Name="Inputs" />
        <Component Name="I_Stamp_Up" />
      </Symbol>
    </Access>
    <Access Scope="GlobalVariable" UId="24">
      <Symbol>
        <Component Name="Global DB" />
        <Component Name="Inputs" />
        <Component Name="I_Conveyor_Metal" />
      </Symbol>
    </Access>
    <Access Scope="GlobalVariable" UId="25">
      <Symbol>
        <Component Name="Global DB" />
        <Component Name="Inputs" />
        <Component Name="I_Gripper_at_Stamp" />
      </Symbol>
    </Access>
    <Access Scope="TypedConstant" UId="26">
      <Constant>
        <ConstantValue>T#1s</ConstantValue>
      </Constant>
    </Access>
    <Access Scope="GlobalVariable" UId="27">
      <Symbol>
        <Component Name="VC" />
        <Component Name="Start Simulation" />
      </Symbol>
    </Access>
    <Access Scope="GlobalVariable" UId="28">
      <Symbol>
        <Component Name="Global DB" />
        <Component Name="Inputs" />
        <Component Name="I_Gripper_at_Stamp" />
      </Symbol>
    </Access>
    <Access Scope="LocalVariable" UId="29">
      <Symbol>
        <Component Name="Process" />
        <Component Name="Stamp_Done" />
      </Symbol>
    </Access>
    <Access Scope="LocalVariable" UId="30">
      <Symbol>
        <Component Name="Process" />
        <Component Name="Gripper_Opens_at_Stamp" />
      </Symbol>
    </Access>
    <Part Name="A" UId="31">
      <TemplateValue Name="Card" Type="Cardinality">5</TemplateValue>
    </Part>
    <Part Name="TON" Version="1.0" UId="32">
      <Instance Scope="GlobalVariable" UId="33">
        <Component Name="IEC_Timer_0_DB_19" />
      </Instance>
      <TemplateValue Name="time_type" Type="Type">Time</TemplateValue>
    </Part>
    <Part Name="O" UId="34">
      <TemplateValue Name="Card" Type="Cardinality">3</TemplateValue>
      <Negated Name="in1" />
      <Negated Name="in2" />
    </Part>
    <Part Name="Sr" UId="35" />
  </Parts>
  <Wires>
    <Wire UId="37">
      <IdentCon UId="21" />
      <NameCon UId="31" Name="in1" />
    </Wire>
    <Wire UId="38">
      <IdentCon UId="22" />
      <NameCon UId="31" Name="in2" />
    </Wire>
    <Wire UId="39">
      <IdentCon UId="23" />
      <NameCon UId="31" Name="in3" />
    </Wire>
    <Wire UId="40">
      <IdentCon UId="24" />
      <NameCon UId="31" Name="in4" />
    </Wire>
    <Wire UId="41">
      <IdentCon UId="25" />
      <NameCon UId="31" Name="in5" />
    </Wire>
    <Wire UId="42">
      <NameCon UId="31" Name="out" />
      <NameCon UId="32" Name="IN" />
    </Wire>
    <Wire UId="43">
      <IdentCon UId="26" />
      <NameCon UId="32" Name="PT" />
    </Wire>
    <Wire UId="44">
      <NameCon UId="32" Name="ET" />
      <OpenCon UId="36" />
    </Wire>
    <Wire UId="45">
      <NameCon UId="32" Name="Q" />
      <NameCon UId="35" Name="s" />
    </Wire>
    <Wire UId="46">
      <IdentCon UId="27" />
      <NameCon UId="34" Name="in1" />
    </Wire>
    <Wire UId="47">
      <IdentCon UId="28" />
      <NameCon UId="34" Name="in2" />
    </Wire>
    <Wire UId="48">
      <IdentCon UId="29" />
      <NameCon UId="34" Name="in3" />
    </Wire>
    <Wire UId="49">
      <NameCon UId="34" Name="out" />
      <NameCon UId="35" Name="r1" />
    </Wire>
    <Wire UId="50">
      <IdentCon UId="30" />
      <NameCon UId="35" Name="operand" />
    </Wire>
  </Wires>
</FlgNet></NetworkSource>
          <ProgrammingLanguage>FBD</ProgrammingLanguage>
        </AttributeList>
        <ObjectList>
          <MultilingualText ID="22" CompositionName="Comment">
            <ObjectList>
              <MultilingualTextItem ID="23" CompositionName="Items">
                <AttributeList>
                  <Culture>de-DE</Culture>
                  <Text />
                </AttributeList>
              </MultilingualTextItem>
            </ObjectList>
          </MultilingualText>
          <MultilingualText ID="24" CompositionName="Title">
            <ObjectList>
              <MultilingualTextItem ID="25" CompositionName="Items">
                <AttributeList>
                  <Culture>de-DE</Culture>
                  <Text />
                </AttributeList>
              </MultilingualTextItem>
            </ObjectList>
          </MultilingualText>
        </ObjectList>
      </SW.Blocks.CompileUnit>
      <SW.Blocks.CompileUnit ID="26" CompositionName="CompileUnits">
        <AttributeList>
          <NetworkSource><FlgNet xmlns="http://www.siemens.com/automation/Openness/SW/NetworkSource/FlgNet/v4">
  <Parts>
    <Access Scope="GlobalVariable" UId="21">
      <Symbol>
        <Component Name="VC" />
        <Component Name="Start Simulation" />
      </Symbol>
    </Access>
    <Access Scope="GlobalVariable" UId="22">
      <Symbol>
        <Component Name="Global DB" />
        <Component Name="Inputs" />
        <Component Name="I_Gripper_at_Stamp" />
      </Symbol>
    </Access>
    <Access Scope="GlobalVariable" UId="23">
      <Symbol>
        <Component Name="Global DB" />
        <Component Name="Inputs" />
        <Component Name="I_Cylinder_Gripper_Down" />
      </Symbol>
    </Access>
    <Access Scope="TypedConstant" UId="24">
      <Constant>
        <ConstantValue>T#1s</ConstantValue>
      </Constant>
    </Access>
    <Access Scope="GlobalVariable" UId="25">
      <Symbol>
        <Component Name="VC" />
        <Component Name="Start Simulation" />
      </Symbol>
    </Access>
    <Access Scope="LocalVariable" UId="26">
      <Symbol>
        <Component Name="Process" />
        <Component Name="Stamp_Done" />
      </Symbol>
    </Access>
    <Access Scope="LocalVariable" UId="27">
      <Symbol>
        <Component Name="Process" />
        <Component Name="Stamping" />
      </Symbol>
    </Access>
    <Part Name="A" UId="28">
      <TemplateValue Name="Card" Type="Cardinality">3</TemplateValue>
    </Part>
    <Part Name="TON" Version="1.0" UId="29">
      <Instance Scope="GlobalVariable" UId="30">
        <Component Name="IEC_Timer_0_DB_20" />
      </Instance>
      <TemplateValue Name="time_type" Type="Type">Time</TemplateValue>
    </Part>
    <Part Name="O" UId="31">
      <TemplateValue Name="Card" Type="Cardinality">2</TemplateValue>
      <Negated Name="in1" />
    </Part>
    <Part Name="Sr" UId="32" />
  </Parts>
  <Wires>
    <Wire UId="34">
      <IdentCon UId="21" />
      <NameCon UId="28" Name="in1" />
    </Wire>
    <Wire UId="35">
      <IdentCon UId="22" />
      <NameCon UId="28" Name="in2" />
    </Wire>
    <Wire UId="36">
      <IdentCon UId="23" />
      <NameCon UId="28" Name="in3" />
    </Wire>
    <Wire UId="37">
      <NameCon UId="28" Name="out" />
      <NameCon UId="29" Name="IN" />
    </Wire>
    <Wire UId="38">
      <IdentCon UId="24" />
      <NameCon UId="29" Name="PT" />
    </Wire>
    <Wire UId="39">
      <NameCon UId="29" Name="ET" />
      <OpenCon UId="33" />
    </Wire>
    <Wire UId="40">
      <NameCon UId="29" Name="Q" />
      <NameCon UId="32" Name="s" />
    </Wire>
    <Wire UId="41">
      <IdentCon UId="25" />
      <NameCon UId="31" Name="in1" />
    </Wire>
    <Wire UId="42">
      <IdentCon UId="26" />
      <NameCon UId="31" Name="in2" />
    </Wire>
    <Wire UId="43">
      <NameCon UId="31" Name="out" />
      <NameCon UId="32" Name="r1" />
    </Wire>
    <Wire UId="44">
      <IdentCon UId="27" />
      <NameCon UId="32" Name="operand" />
    </Wire>
  </Wires>
</FlgNet></NetworkSource>
          <ProgrammingLanguage>FBD</ProgrammingLanguage>
        </AttributeList>
        <ObjectList>
          <MultilingualText ID="27" CompositionName="Comment">
            <ObjectList>
              <MultilingualTextItem ID="28" CompositionName="Items">
                <AttributeList>
                  <Culture>de-DE</Culture>
                  <Text />
                </AttributeList>
              </MultilingualTextItem>
            </ObjectList>
          </MultilingualText>
          <MultilingualText ID="29" CompositionName="Title">
            <ObjectList>
              <MultilingualTextItem ID="2A" CompositionName="Items">
                <AttributeList>
                  <Culture>de-DE</Culture>
                  <Text />
                </AttributeList>
              </MultilingualTextItem>
            </ObjectList>
          </MultilingualText>
        </ObjectList>
      </SW.Blocks.CompileUnit>
      <SW.Blocks.CompileUnit ID="2B" CompositionName="CompileUnits">
        <AttributeList>
          <NetworkSource><FlgNet xmlns="http://www.siemens.com/automation/Openness/SW/NetworkSource/FlgNet/v4">
  <Parts>
    <Access Scope="GlobalVariable" UId="21">
      <Symbol>
        <Component Name="VC" />
        <Component Name="Start Simulation" />
      </Symbol>
    </Access>
    <Access Scope="LocalVariable" UId="22">
      <Symbol>
        <Component Name="Process" />
        <Component Name="Stamping" />
      </Symbol>
    </Access>
    <Access Scope="TypedConstant" UId="23">
      <Constant>
        <ConstantValue>T#2s</ConstantValue>
      </Constant>
    </Access>
    <Access Scope="GlobalVariable" UId="24">
      <Symbol>
        <Component Name="VC" />
        <Component Name="Start Simulation" />
      </Symbol>
    </Access>
    <Access Scope="LocalVariable" UId="25">
      <Symbol>
        <Component Name="Process" />
        <Component Name="Stamp_Done" />
      </Symbol>
    </Access>
    <Part Name="A" UId="26">
      <TemplateValue Name="Card" Type="Cardinality">2</TemplateValue>
    </Part>
    <Part Name="TON" Version="1.0" UId="27">
      <Instance Scope="GlobalVariable" UId="28">
        <Component Name="IEC_Timer_0_DB_21" />
      </Instance>
      <TemplateValue Name="time_type" Type="Type">Time</TemplateValue>
    </Part>
    <Part Name="Sr" UId="29">
      <Negated Name="r1" />
    </Part>
  </Parts>
  <Wires>
    <Wire UId="31">
      <IdentCon UId="21" />
      <NameCon UId="26" Name="in1" />
    </Wire>
    <Wire UId="32">
      <IdentCon UId="22" />
      <NameCon UId="26" Name="in2" />
    </Wire>
    <Wire UId="33">
      <NameCon UId="26" Name="out" />
      <NameCon UId="27" Name="IN" />
    </Wire>
    <Wire UId="34">
      <IdentCon UId="23" />
      <NameCon UId="27" Name="PT" />
    </Wire>
    <Wire UId="35">
      <NameCon UId="27" Name="ET" />
      <OpenCon UId="30" />
    </Wire>
    <Wire UId="36">
      <NameCon UId="27" Name="Q" />
      <NameCon UId="29" Name="s" />
    </Wire>
    <Wire UId="37">
      <IdentCon UId="24" />
      <NameCon UId="29" Name="r1" />
    </Wire>
    <Wire UId="38">
      <IdentCon UId="25" />
      <NameCon UId="29" Name="operand" />
    </Wire>
  </Wires>
</FlgNet></NetworkSource>
          <ProgrammingLanguage>FBD</ProgrammingLanguage>
        </AttributeList>
        <ObjectList>
          <MultilingualText ID="2C" CompositionName="Comment">
            <ObjectList>
              <MultilingualTextItem ID="2D" CompositionName="Items">
                <AttributeList>
                  <Culture>de-DE</Culture>
                  <Text />
                </AttributeList>
              </MultilingualTextItem>
            </ObjectList>
          </MultilingualText>
          <MultilingualText ID="2E" CompositionName="Title">
            <ObjectList>
              <MultilingualTextItem ID="2F" CompositionName="Items">
                <AttributeList>
                  <Culture>de-DE</Culture>
                  <Text />
                </AttributeList>
              </MultilingualTextItem>
            </ObjectList>
          </MultilingualText>
        </ObjectList>
      </SW.Blocks.CompileUnit>
      <SW.Blocks.CompileUnit ID="30" CompositionName="CompileUnits">
        <AttributeList>
          <NetworkSource><FlgNet xmlns="http://www.siemens.com/automation/Openness/SW/NetworkSource/FlgNet/v4">
  <Parts>
    <Access Scope="GlobalVariable" UId="21">
      <Symbol>
        <Component Name="VC" />
        <Component Name="Start Simulation" />
      </Symbol>
    </Access>
    <Access Scope="LocalVariable" UId="22">
      <Symbol>
        <Component Name="Process" />
        <Component Name="Stamp_Done" />
      </Symbol>
    </Access>
    <Access Scope="GlobalVariable" UId="23">
      <Symbol>
        <Component Name="Global DB" />
        <Component Name="Inputs" />
        <Component Name="I_Gripper_at_Stamp" />
      </Symbol>
    </Access>
    <Access Scope="GlobalVariable" UId="24">
      <Symbol>
        <Component Name="Global DB" />
        <Component Name="Inputs" />
        <Component Name="I_Stamp_Up" />
      </Symbol>
    </Access>
    <Access Scope="GlobalVariable" UId="25">
      <Symbol>
        <Component Name="Global DB" />
        <Component Name="Inputs" />
        <Component Name="I_Cylinder_Gripper_Down" />
      </Symbol>
    </Access>
    <Access Scope="TypedConstant" UId="26">
      <Constant>
        <ConstantValue>T#1s</ConstantValue>
      </Constant>
    </Access>
    <Access Scope="GlobalVariable" UId="27">
      <Symbol>
        <Component Name="VC" />
        <Component Name="Start Simulation" />
      </Symbol>
    </Access>
    <Access Scope="LocalVariable" UId="28">
      <Symbol>
        <Component Name="Process" />
        <Component Name="Gripper_Closes_at_Stamp" />
      </Symbol>
    </Access>
    <Part Name="A" UId="29">
      <TemplateValue Name="Card" Type="Cardinality">5</TemplateValue>
    </Part>
    <Part Name="TON" Version="1.0" UId="30">
      <Instance Scope="GlobalVariable" UId="31">
        <Component Name="IEC_Timer_0_DB_22" />
      </Instance>
      <TemplateValue Name="time_type" Type="Type">Time</TemplateValue>
    </Part>
    <Part Name="Sr" UId="32">
      <Negated Name="r1" />
    </Part>
  </Parts>
  <Wires>
    <Wire UId="34">
      <IdentCon UId="21" />
      <NameCon UId="29" Name="in1" />
    </Wire>
    <Wire UId="35">
      <IdentCon UId="22" />
      <NameCon UId="29" Name="in2" />
    </Wire>
    <Wire UId="36">
      <IdentCon UId="23" />
      <NameCon UId="29" Name="in3" />
    </Wire>
    <Wire UId="37">
      <IdentCon UId="24" />
      <NameCon UId="29" Name="in4" />
    </Wire>
    <Wire UId="38">
      <IdentCon UId="25" />
      <NameCon UId="29" Name="in5" />
    </Wire>
    <Wire UId="39">
      <NameCon UId="29" Name="out" />
      <NameCon UId="30" Name="IN" />
    </Wire>
    <Wire UId="40">
      <IdentCon UId="26" />
      <NameCon UId="30" Name="PT" />
    </Wire>
    <Wire UId="41">
      <NameCon UId="30" Name="ET" />
      <OpenCon UId="33" />
    </Wire>
    <Wire UId="42">
      <NameCon UId="30" Name="Q" />
      <NameCon UId="32" Name="s" />
    </Wire>
    <Wire UId="43">
      <IdentCon UId="27" />
      <NameCon UId="32" Name="r1" />
    </Wire>
    <Wire UId="44">
      <IdentCon UId="28" />
      <NameCon UId="32" Name="operand" />
    </Wire>
  </Wires>
</FlgNet></NetworkSource>
          <ProgrammingLanguage>FBD</ProgrammingLanguage>
        </AttributeList>
        <ObjectList>
          <MultilingualText ID="31" CompositionName="Comment">
            <ObjectList>
              <MultilingualTextItem ID="32" CompositionName="Items">
                <AttributeList>
                  <Culture>de-DE</Culture>
                  <Text />
                </AttributeList>
              </MultilingualTextItem>
            </ObjectList>
          </MultilingualText>
          <MultilingualText ID="33" CompositionName="Title">
            <ObjectList>
              <MultilingualTextItem ID="34" CompositionName="Items">
                <AttributeList>
                  <Culture>de-DE</Culture>
                  <Text />
                </AttributeList>
              </MultilingualTextItem>
            </ObjectList>
          </MultilingualText>
        </ObjectList>
      </SW.Blocks.CompileUnit>
      <SW.Blocks.CompileUnit ID="35" CompositionName="CompileUnits">
        <AttributeList>
          <NetworkSource><FlgNet xmlns="http://www.siemens.com/automation/Openness/SW/NetworkSource/FlgNet/v4">
  <Parts>
    <Access Scope="GlobalVariable" UId="21">
      <Symbol>
        <Component Name="VC" />
        <Component Name="Start Simulation" />
      </Symbol>
    </Access>
    <Access Scope="GlobalVariable" UId="22">
      <Symbol>
        <Component Name="Global DB" />
        <Component Name="Inputs" />
        <Component Name="I_Cylinder_Gripper_Down" />
      </Symbol>
    </Access>
    <Access Scope="GlobalVariable" UId="23">
      <Symbol>
        <Component Name="Global DB" />
        <Component Name="Inputs" />
        <Component Name="I_Gripper_at_Stamp" />
      </Symbol>
    </Access>
    <Access Scope="LocalVariable" UId="24">
      <Symbol>
        <Component Name="Process" />
        <Component Name="Stamp_Done" />
      </Symbol>
    </Access>
    <Access Scope="GlobalVariable" UId="25">
      <Symbol>
        <Component Name="Global DB" />
        <Component Name="Inputs" />
        <Component Name="I_Stamp_Up" />
      </Symbol>
    </Access>
    <Access Scope="TypedConstant" UId="26">
      <Constant>
        <ConstantValue>T#2s</ConstantValue>
      </Constant>
    </Access>
    <Access Scope="GlobalVariable" UId="27">
      <Symbol>
        <Component Name="VC" />
        <Component Name="Start Simulation" />
      </Symbol>
    </Access>
    <Access Scope="GlobalVariable" UId="28">
      <Symbol>
        <Component Name="Global DB" />
        <Component Name="Inputs" />
        <Component Name="I_Cylinder_Gripper_Up" />
      </Symbol>
    </Access>
    <Access Scope="LocalVariable" UId="29">
      <Symbol>
        <Component Name="Process" />
        <Component Name="Gripper_Going_Up_At_Stamp" />
      </Symbol>
    </Access>
    <Part Name="A" UId="30">
      <TemplateValue Name="Card" Type="Cardinality">5</TemplateValue>
    </Part>
    <Part Name="TON" Version="1.0" UId="31">
      <Instance Scope="GlobalVariable" UId="32">
        <Component Name="IEC_Timer_0_DB_23" />
      </Instance>
      <TemplateValue Name="time_type" Type="Type">Time</TemplateValue>
    </Part>
    <Part Name="O" UId="33">
      <TemplateValue Name="Card" Type="Cardinality">2</TemplateValue>
      <Negated Name="in1" />
    </Part>
    <Part Name="Sr" UId="34" />
  </Parts>
  <Wires>
    <Wire UId="36">
      <IdentCon UId="21" />
      <NameCon UId="30" Name="in1" />
    </Wire>
    <Wire UId="37">
      <IdentCon UId="22" />
      <NameCon UId="30" Name="in2" />
    </Wire>
    <Wire UId="38">
      <IdentCon UId="23" />
      <NameCon UId="30" Name="in3" />
    </Wire>
    <Wire UId="39">
      <IdentCon UId="24" />
      <NameCon UId="30" Name="in4" />
    </Wire>
    <Wire UId="40">
      <IdentCon UId="25" />
      <NameCon UId="30" Name="in5" />
    </Wire>
    <Wire UId="41">
      <NameCon UId="30" Name="out" />
      <NameCon UId="31" Name="IN" />
    </Wire>
    <Wire UId="42">
      <IdentCon UId="26" />
      <NameCon UId="31" Name="PT" />
    </Wire>
    <Wire UId="43">
      <NameCon UId="31" Name="ET" />
      <OpenCon UId="35" />
    </Wire>
    <Wire UId="44">
      <NameCon UId="31" Name="Q" />
      <NameCon UId="34" Name="s" />
    </Wire>
    <Wire UId="45">
      <IdentCon UId="27" />
      <NameCon UId="33" Name="in1" />
    </Wire>
    <Wire UId="46">
      <IdentCon UId="28" />
      <NameCon UId="33" Name="in2" />
    </Wire>
    <Wire UId="47">
      <NameCon UId="33" Name="out" />
      <NameCon UId="34" Name="r1" />
    </Wire>
    <Wire UId="48">
      <IdentCon UId="29" />
      <NameCon UId="34" Name="operand" />
    </Wire>
  </Wires>
</FlgNet></NetworkSource>
          <ProgrammingLanguage>FBD</ProgrammingLanguage>
        </AttributeList>
        <ObjectList>
          <MultilingualText ID="36" CompositionName="Comment">
            <ObjectList>
              <MultilingualTextItem ID="37" CompositionName="Items">
                <AttributeList>
                  <Culture>de-DE</Culture>
                  <Text />
                </AttributeList>
              </MultilingualTextItem>
            </ObjectList>
          </MultilingualText>
          <MultilingualText ID="38" CompositionName="Title">
            <ObjectList>
              <MultilingualTextItem ID="39" CompositionName="Items">
                <AttributeList>
                  <Culture>de-DE</Culture>
                  <Text />
                </AttributeList>
              </MultilingualTextItem>
            </ObjectList>
          </MultilingualText>
        </ObjectList>
      </SW.Blocks.CompileUnit>
      <SW.Blocks.CompileUnit ID="3A" CompositionName="CompileUnits">
        <AttributeList>
          <NetworkSource><FlgNet xmlns="http://www.siemens.com/automation/Openness/SW/NetworkSource/FlgNet/v4">
  <Parts>
    <Access Scope="GlobalVariable" UId="21">
      <Symbol>
        <Component Name="VC" />
        <Component Name="Start Simulation" />
      </Symbol>
    </Access>
    <Access Scope="GlobalVariable" UId="22">
      <Symbol>
        <Component Name="Global DB" />
        <Component Name="Inputs" />
        <Component Name="I_Stamp_Up" />
      </Symbol>
    </Access>
    <Access Scope="GlobalVariable" UId="23">
      <Symbol>
        <Component Name="Global DB" />
        <Component Name="Inputs" />
        <Component Name="I_Cylinder_Gripper_Up" />
      </Symbol>
    </Access>
    <Access Scope="LocalVariable" UId="24">
      <Symbol>
        <Component Name="Process" />
        <Component Name="Stamp_Done" />
      </Symbol>
    </Access>
    <Access Scope="LocalVariable" UId="25">
      <Symbol>
        <Component Name="Process" />
        <Component Name="Ready_to_Move_to_Storage" />
      </Symbol>
    </Access>
    <Access Scope="LocalVariable" UId="26">
      <Symbol>
        <Component Name="Process" />
        <Component Name="Ready_to_Move_to_Storage" />
      </Symbol>
    </Access>
    <Access Scope="GlobalVariable" UId="27">
      <Symbol>
        <Component Name="Global DB" />
        <Component Name="Inputs" />
        <Component Name="I_Stamp_Up" />
      </Symbol>
    </Access>
    <Access Scope="GlobalVariable" UId="28">
      <Symbol>
        <Component Name="Global DB" />
        <Component Name="Inputs" />
        <Component Name="I_Cylinder_Gripper_Up" />
      </Symbol>
    </Access>
    <Access Scope="GlobalVariable" UId="29">
      <Symbol>
        <Component Name="Global DB" />
        <Component Name="Inputs" />
        <Component Name="I_Conveyor_Plastic" />
      </Symbol>
    </Access>
    <Access Scope="TypedConstant" UId="30">
      <Constant>
        <ConstantValue>T#1s</ConstantValue>
      </Constant>
    </Access>
    <Access Scope="GlobalVariable" UId="31">
      <Symbol>
        <Component Name="VC" />
        <Component Name="Start Simulation" />
      </Symbol>
    </Access>
    <Access Scope="GlobalVariable" UId="32">
      <Symbol>
        <Component Name="Global DB" />
        <Component Name="Inputs" />
        <Component Name="I_Axis_End_Right" />
      </Symbol>
    </Access>
    <Access Scope="LocalVariable" UId="33">
      <Symbol>
        <Component Name="Process" />
        <Component Name="Going_To_Storage" />
      </Symbol>
    </Access>
    <Part Name="A" UId="34">
      <TemplateValue Name="Card" Type="Cardinality">5</TemplateValue>
    </Part>
    <Part Name="A" UId="35">
      <TemplateValue Name="Card" Type="Cardinality">4</TemplateValue>
    </Part>
    <Part Name="O" UId="36">
      <TemplateValue Name="Card" Type="Cardinality">2</TemplateValue>
    </Part>
    <Part Name="TON" Version="1.0" UId="37">
      <Instance Scope="GlobalVariable" UId="38">
        <Component Name="IEC_Timer_0_DB_24" />
      </Instance>
      <TemplateValue Name="time_type" Type="Type">Time</TemplateValue>
    </Part>
    <Part Name="O" UId="39">
      <TemplateValue Name="Card" Type="Cardinality">2</TemplateValue>
      <Negated Name="in1" />
    </Part>
    <Part Name="Sr" UId="40" />
  </Parts>
  <Wires>
    <Wire UId="42">
      <IdentCon UId="21" />
      <NameCon UId="34" Name="in1" />
    </Wire>
    <Wire UId="43">
      <IdentCon UId="22" />
      <NameCon UId="34" Name="in2" />
    </Wire>
    <Wire UId="44">
      <IdentCon UId="23" />
      <NameCon UId="34" Name="in3" />
    </Wire>
    <Wire UId="45">
      <IdentCon UId="24" />
      <NameCon UId="34" Name="in4" />
    </Wire>
    <Wire UId="46">
      <IdentCon UId="25" />
      <NameCon UId="34" Name="in5" />
    </Wire>
    <Wire UId="47">
      <NameCon UId="34" Name="out" />
      <NameCon UId="36" Name="in1" />
    </Wire>
    <Wire UId="48">
      <IdentCon UId="26" />
      <NameCon UId="35" Name="in1" />
    </Wire>
    <Wire UId="49">
      <IdentCon UId="27" />
      <NameCon UId="35" Name="in2" />
    </Wire>
    <Wire UId="50">
      <IdentCon UId="28" />
      <NameCon UId="35" Name="in3" />
    </Wire>
    <Wire UId="51">
      <IdentCon UId="29" />
      <NameCon UId="35" Name="in4" />
    </Wire>
    <Wire UId="52">
      <NameCon UId="35" Name="out" />
      <NameCon UId="36" Name="in2" />
    </Wire>
    <Wire UId="53">
      <NameCon UId="36" Name="out" />
      <NameCon UId="37" Name="IN" />
    </Wire>
    <Wire UId="54">
      <IdentCon UId="30" />
      <NameCon UId="37" Name="PT" />
    </Wire>
    <Wire UId="55">
      <NameCon UId="37" Name="ET" />
      <OpenCon UId="41" />
    </Wire>
    <Wire UId="56">
      <NameCon UId="37" Name="Q" />
      <NameCon UId="40" Name="s" />
    </Wire>
    <Wire UId="57">
      <IdentCon UId="31" />
      <NameCon UId="39" Name="in1" />
    </Wire>
    <Wire UId="58">
      <IdentCon UId="32" />
      <NameCon UId="39" Name="in2" />
    </Wire>
    <Wire UId="59">
      <NameCon UId="39" Name="out" />
      <NameCon UId="40" Name="r1" />
    </Wire>
    <Wire UId="60">
      <IdentCon UId="33" />
      <NameCon UId="40" Name="operand" />
    </Wire>
  </Wires>
</FlgNet></NetworkSource>
          <ProgrammingLanguage>FBD</ProgrammingLanguage>
        </AttributeList>
        <ObjectList>
          <MultilingualText ID="3B" CompositionName="Comment">
            <ObjectList>
              <MultilingualTextItem ID="3C" CompositionName="Items">
                <AttributeList>
                  <Culture>de-DE</Culture>
                  <Text />
                </AttributeList>
              </MultilingualTextItem>
            </ObjectList>
          </MultilingualText>
          <MultilingualText ID="3D" CompositionName="Title">
            <ObjectList>
              <MultilingualTextItem ID="3E" CompositionName="Items">
                <AttributeList>
                  <Culture>de-DE</Culture>
                  <Text />
                </AttributeList>
              </MultilingualTextItem>
            </ObjectList>
          </MultilingualText>
        </ObjectList>
      </SW.Blocks.CompileUnit>
      <SW.Blocks.CompileUnit ID="3F" CompositionName="CompileUnits">
        <AttributeList>
          <NetworkSource><FlgNet xmlns="http://www.siemens.com/automation/Openness/SW/NetworkSource/FlgNet/v4">
  <Parts>
    <Access Scope="GlobalVariable" UId="21">
      <Symbol>
        <Component Name="VC" />
        <Component Name="Start Simulation" />
      </Symbol>
    </Access>
    <Access Scope="GlobalVariable" UId="22">
      <Symbol>
        <Component Name="Global DB" />
        <Component Name="Inputs" />
        <Component Name="I_Axis_End_Right" />
      </Symbol>
    </Access>
    <Access Scope="TypedConstant" UId="23">
      <Constant>
        <ConstantValue>T#1s</ConstantValue>
      </Constant>
    </Access>
    <Access Scope="GlobalVariable" UId="24">
      <Symbol>
        <Component Name="VC" />
        <Component Name="Start Simulation" />
      </Symbol>
    </Access>
    <Access Scope="GlobalVariable" UId="25">
      <Symbol>
        <Component Name="Global DB" />
        <Component Name="Inputs" />
        <Component Name="I_Cylinder_Gripper_Down" />
      </Symbol>
    </Access>
    <Access Scope="LocalVariable" UId="26">
      <Symbol>
        <Component Name="Process" />
        <Component Name="At_Storage" />
      </Symbol>
    </Access>
    <Part Name="A" UId="27">
      <TemplateValue Name="Card" Type="Cardinality">2</TemplateValue>
    </Part>
    <Part Name="TON" Version="1.0" UId="28">
      <Instance Scope="GlobalVariable" UId="29">
        <Component Name="IEC_Timer_0_DB_25" />
      </Instance>
      <TemplateValue Name="time_type" Type="Type">Time</TemplateValue>
    </Part>
    <Part Name="O" UId="30">
      <TemplateValue Name="Card" Type="Cardinality">2</TemplateValue>
      <Negated Name="in1" />
    </Part>
    <Part Name="Sr" UId="31" />
  </Parts>
  <Wires>
    <Wire UId="33">
      <IdentCon UId="21" />
      <NameCon UId="27" Name="in1" />
    </Wire>
    <Wire UId="34">
      <IdentCon UId="22" />
      <NameCon UId="27" Name="in2" />
    </Wire>
    <Wire UId="35">
      <NameCon UId="27" Name="out" />
      <NameCon UId="28" Name="IN" />
    </Wire>
    <Wire UId="36">
      <IdentCon UId="23" />
      <NameCon UId="28" Name="PT" />
    </Wire>
    <Wire UId="37">
      <NameCon UId="28" Name="ET" />
      <OpenCon UId="32" />
    </Wire>
    <Wire UId="38">
      <NameCon UId="28" Name="Q" />
      <NameCon UId="31" Name="s" />
    </Wire>
    <Wire UId="39">
      <IdentCon UId="24" />
      <NameCon UId="30" Name="in1" />
    </Wire>
    <Wire UId="40">
      <IdentCon UId="25" />
      <NameCon UId="30" Name="in2" />
    </Wire>
    <Wire UId="41">
      <NameCon UId="30" Name="out" />
      <NameCon UId="31" Name="r1" />
    </Wire>
    <Wire UId="42">
      <IdentCon UId="26" />
      <NameCon UId="31" Name="operand" />
    </Wire>
  </Wires>
</FlgNet></NetworkSource>
          <ProgrammingLanguage>FBD</ProgrammingLanguage>
        </AttributeList>
        <ObjectList>
          <MultilingualText ID="40" CompositionName="Comment">
            <ObjectList>
              <MultilingualTextItem ID="41" CompositionName="Items">
                <AttributeList>
                  <Culture>de-DE</Culture>
                  <Text />
                </AttributeList>
              </MultilingualTextItem>
            </ObjectList>
          </MultilingualText>
          <MultilingualText ID="42" CompositionName="Title">
            <ObjectList>
              <MultilingualTextItem ID="43" CompositionName="Items">
                <AttributeList>
                  <Culture>de-DE</Culture>
                  <Text />
                </AttributeList>
              </MultilingualTextItem>
            </ObjectList>
          </MultilingualText>
        </ObjectList>
      </SW.Blocks.CompileUnit>
      <SW.Blocks.CompileUnit ID="44" CompositionName="CompileUnits">
        <AttributeList>
          <NetworkSource><FlgNet xmlns="http://www.siemens.com/automation/Openness/SW/NetworkSource/FlgNet/v4">
  <Parts>
    <Access Scope="GlobalVariable" UId="21">
      <Symbol>
        <Component Name="VC" />
        <Component Name="Start Simulation" />
      </Symbol>
    </Access>
    <Access Scope="GlobalVariable" UId="22">
      <Symbol>
        <Component Name="Global DB" />
        <Component Name="Inputs" />
        <Component Name="I_Cylinder_Gripper_Down" />
      </Symbol>
    </Access>
    <Access Scope="GlobalVariable" UId="23">
      <Symbol>
        <Component Name="Global DB" />
        <Component Name="Inputs" />
        <Component Name="I_Axis_End_Right" />
      </Symbol>
    </Access>
    <Access Scope="TypedConstant" UId="24">
      <Constant>
        <ConstantValue>T#1s</ConstantValue>
      </Constant>
    </Access>
    <Access Scope="GlobalVariable" UId="25">
      <Symbol>
        <Component Name="VC" />
        <Component Name="Start Simulation" />
      </Symbol>
    </Access>
    <Access Scope="LocalVariable" UId="26">
      <Symbol>
        <Component Name="Process" />
        <Component Name="Release_Part" />
      </Symbol>
    </Access>
    <Part Name="A" UId="27">
      <TemplateValue Name="Card" Type="Cardinality">3</TemplateValue>
    </Part>
    <Part Name="TON" Version="1.0" UId="28">
      <Instance Scope="GlobalVariable" UId="29">
        <Component Name="IEC_Timer_0_DB_26" />
      </Instance>
      <TemplateValue Name="time_type" Type="Type">Time</TemplateValue>
    </Part>
    <Part Name="Sr" UId="30">
      <Negated Name="r1" />
    </Part>
  </Parts>
  <Wires>
    <Wire UId="32">
      <IdentCon UId="21" />
      <NameCon UId="27" Name="in1" />
    </Wire>
    <Wire UId="33">
      <IdentCon UId="22" />
      <NameCon UId="27" Name="in2" />
    </Wire>
    <Wire UId="34">
      <IdentCon UId="23" />
      <NameCon UId="27" Name="in3" />
    </Wire>
    <Wire UId="35">
      <NameCon UId="27" Name="out" />
      <NameCon UId="28" Name="IN" />
    </Wire>
    <Wire UId="36">
      <IdentCon UId="24" />
      <NameCon UId="28" Name="PT" />
    </Wire>
    <Wire UId="37">
      <NameCon UId="28" Name="ET" />
      <OpenCon UId="31" />
    </Wire>
    <Wire UId="38">
      <NameCon UId="28" Name="Q" />
      <NameCon UId="30" Name="s" />
    </Wire>
    <Wire UId="39">
      <IdentCon UId="25" />
      <NameCon UId="30" Name="r1" />
    </Wire>
    <Wire UId="40">
      <IdentCon UId="26" />
      <NameCon UId="30" Name="operand" />
    </Wire>
  </Wires>
</FlgNet></NetworkSource>
          <ProgrammingLanguage>FBD</ProgrammingLanguage>
        </AttributeList>
        <ObjectList>
          <MultilingualText ID="45" CompositionName="Comment">
            <ObjectList>
              <MultilingualTextItem ID="46" CompositionName="Items">
                <AttributeList>
                  <Culture>de-DE</Culture>
                  <Text />
                </AttributeList>
              </MultilingualTextItem>
            </ObjectList>
          </MultilingualText>
          <MultilingualText ID="47" CompositionName="Title">
            <ObjectList>
              <MultilingualTextItem ID="48" CompositionName="Items">
                <AttributeList>
                  <Culture>de-DE</Culture>
                  <Text />
                </AttributeList>
              </MultilingualTextItem>
            </ObjectList>
          </MultilingualText>
        </ObjectList>
      </SW.Blocks.CompileUnit>
      <SW.Blocks.CompileUnit ID="49" CompositionName="CompileUnits">
        <AttributeList>
          <NetworkSource />
          <ProgrammingLanguage>FBD</ProgrammingLanguage>
        </AttributeList>
        <ObjectList>
          <MultilingualText ID="4A" CompositionName="Comment">
            <ObjectList>
              <MultilingualTextItem ID="4B" CompositionName="Items">
                <AttributeList>
                  <Culture>de-DE</Culture>
                  <Text />
                </AttributeList>
              </MultilingualTextItem>
            </ObjectList>
          </MultilingualText>
          <MultilingualText ID="4C" CompositionName="Title">
            <ObjectList>
              <MultilingualTextItem ID="4D" CompositionName="Items">
                <AttributeList>
                  <Culture>de-DE</Culture>
                  <Text />
                </AttributeList>
              </MultilingualTextItem>
            </ObjectList>
          </MultilingualText>
        </ObjectList>
      </SW.Blocks.CompileUnit>
      <MultilingualText ID="4E" CompositionName="Title">
        <ObjectList>
          <MultilingualTextItem ID="4F" CompositionName="Items">
            <AttributeList>
              <Culture>de-DE</Culture>
              <Text />
            </AttributeList>
          </MultilingualTextItem>
        </ObjectList>
      </MultilingualText>
    </ObjectList>
  </SW.Blocks.FB>
</Document>